setup.py
dm/__init__.py
dm.zope.rpc.egg-info/PKG-INFO
dm.zope.rpc.egg-info/SOURCES.txt
dm.zope.rpc.egg-info/dependency_links.txt
dm.zope.rpc.egg-info/namespace_packages.txt
dm.zope.rpc.egg-info/not-zip-safe
dm.zope.rpc.egg-info/requires.txt
dm.zope.rpc.egg-info/top_level.txt
dm/zope/__init__.py
dm/zope/rpc/LICENSE.txt
dm/zope/rpc/README.txt
dm/zope/rpc/VERSION.txt
dm/zope/rpc/__init__.py
dm/zope/rpc/adapter.py
dm/zope/rpc/handler.py
dm/zope/rpc/interfaces.py
dm/zope/rpc/marshaller.py
dm/zope/rpc/namespace.py
dm/zope/rpc/response.py
dm/zope/rpc/type.py
dm/zope/rpc/util.py
dm/zope/rpc/protocol/__init__.py
dm/zope/rpc/protocol/jsonrpc.py
dm/zope/rpc/protocol/jsonrpcproxy.py
dm/zope/rpc/protocol/reprrpc.py
dm/zope/rpc/protocol/xmlrpc.py
dm/zope/rpc/tests/__init__.py
dm/zope/rpc/tests/adapter.txt
dm/zope/rpc/tests/test_adapter.py
dm/zope/rpc/tests/example/__init__.py
dm/zope/rpc/tests/example/configure.zcml
dm/zope/rpc/tests/example/browser/__init__.py
dm/zope/rpc/tests/example/browser/configure.zcml
dm/zope/rpc/tests/example/browser/service.py
dm/zope/rpc/tests/xmlrpc/__init__.py
dm/zope/rpc/tests/xmlrpc/configure.zcml
dm/zope/rpc/tests/xmlrpc/browser/__init__.py
dm/zope/rpc/tests/xmlrpc/browser/configure.zcml