Metadata-Version: 1.1
Name: dm.zope.rpc
Version: 1.0
Summary: Remote Procedure Call server support for Zope[2]
Home-page: http://pypi.python.org/pypi/dm.zope.rpc
Author: Dieter Maurer
Author-email: dieter@handshake.de
License: BSD
Keywords: rpc zope multiprotocol
Platform: UNKNOWN
Classifier: Development Status :: 5 - Production/Stable
Classifier: Intended Audience :: Developers
Classifier: License :: OSI Approved :: BSD License
Classifier: Framework :: Zope2
Classifier: Operating System :: OS Independent
Classifier: Programming Language :: Python :: 2.4
Classifier: Programming Language :: Python :: 2.6
Classifier: Topic :: Utilities
